authentikate/__init__.py
authentikate/admin.py
authentikate/apps.py
authentikate/base_models.py
authentikate/decode.py
authentikate/errors.py
authentikate/expand.py
authentikate/models.py
authentikate/protocols.py
authentikate/settings.py
authentikate/utils.py
authentikate/vars.py
authentikate/migrations/0001_initial.py
authentikate/migrations/0002_membership.py
authentikate/migrations/0003_app_release_client_release.py
authentikate/migrations/0004_device_client_device.py
authentikate/migrations/__init__.py
authentikate/strawberry/__init__.py
authentikate/strawberry/directives.py
authentikate/strawberry/extension.py
authentikate/strawberry/info.py
authentikate/strawberry/types.py
authentikate-0.32.0.dist-info/METADATA
authentikate-0.32.0.dist-info/WHEEL
authentikate-0.32.0.dist-info/licenses/LICENSE
authentikate-0.32.0.dist-info/RECORD
