Metadata-Version: 2.4
Name: authentikate
Version: 0.32.0
Author-email: jhnnsrs <jhnnsrs@gmail.com>
License-Expression: MIT
License-File: LICENSE
Requires-Python: <4.0,>=3.11
Requires-Dist: django-guardian<3,>=2.4.0
Requires-Dist: django>5
Requires-Dist: joserfc>=1.0.4
Requires-Dist: kante>=0.16
Requires-Dist: pydantic<3,>2
